contactsmanager/__init__.py
contactsmanager/client.py
contactsmanager/server_api.py
contactsmanager/server_config.py
contactsmanager/types.py
contactsmanager/integration_tests/__init__.py
contactsmanager/integration_tests/env_loader.py
contactsmanager/integration_tests/run_tests.py
contactsmanager/integration_tests/test_api_key_validation.py
contactsmanager/integration_tests/test_server_api.py
contactsmanager-1.3.0.dist-info/licenses/LICENSE
contactsmanager-1.3.0.dist-info/METADATA
contactsmanager-1.3.0.dist-info/WHEEL
contactsmanager-1.3.0.dist-info/top_level.txt
contactsmanager-1.3.0.dist-info/RECORD
