Metadata-Version: 2.4
Name: contactsmanager
Version: 1.3.0
Summary: Python SDK for ContactsManager API authentication and token generation
Home-page: https://github.com/arpwal/contactsmanager-py
Author: Arpit Agarwal
Author-email: your-email@example.com
Project-URL: Source, https://github.com/arpwal/contactmanager
Project-URL: Bug Reports, https://github.com/arpwal/contactmanager/issues
Keywords: api,sdk,contactsmanager,authentication,jwt
Classifier: Development Status :: 4 - Beta
Classifier: Intended Audience :: Developers
Classifier: License :: OSI Approved :: MIT License
Classifier: Programming Language :: Python :: 3
Classifier: Programming Language :: Python :: 3.8
Classifier: Programming Language :: Python :: 3.9
Classifier: Programming Language :: Python :: 3.10
Classifier: Programming Language :: Python :: 3.11
Classifier: Programming Language :: Python :: 3.12
Requires-Python: >=3.8
License-File: LICENSE
Requires-Dist: PyJWT<3.0.0,>=2.0.0
Requires-Dist: requests<3.0.0,>=2.28.0
Provides-Extra: dev
Requires-Dist: pytest>=7.0.0; extra == "dev"
Requires-Dist: pytest-cov>=4.0.0; extra == "dev"
Requires-Dist: black>=23.0.0; extra == "dev"
Requires-Dist: isort>=5.12.0; extra == "dev"
Requires-Dist: twine>=4.0.0; extra == "dev"
Requires-Dist: build>=0.10.0; extra == "dev"
Requires-Dist: httpx>=0.24.0; extra == "dev"
Dynamic: author
Dynamic: author-email
Dynamic: classifier
Dynamic: description
Dynamic: description-content-type
Dynamic: home-page
Dynamic: keywords
Dynamic: license-file
Dynamic: project-url
Dynamic: provides-extra
Dynamic: requires-dist
Dynamic: requires-python
Dynamic: summary
